tornet_mp/__init__.py
tornet_mp/__main__.py
tornet_mp/banner.py
tornet_mp/core.py
tornet_mp/log.py
tornet_mp/py.typed
tornet_mp/utils.py
tornet_mp/version.py
tornet_mp-1.0.10.dist-info/licenses/LICENSE
tornet_mp-1.0.10.dist-info/METADATA
tornet_mp-1.0.10.dist-info/WHEEL
tornet_mp-1.0.10.dist-info/entry_points.txt
tornet_mp-1.0.10.dist-info/top_level.txt
tornet_mp-1.0.10.dist-info/RECORD
