Metadata-Version: 2.4
Name: tornet-mp
Version: 1.0.10
Summary: TorNet - Cross-platform IP rotation using Tor with logging and automation
Author-email: Ernesto Leiva <contact@ernestoleiva.com>
License: MIT
Classifier: Programming Language :: Python :: 3
Classifier: License :: OSI Approved :: MIT License
Classifier: Operating System :: OS Independent
Classifier: Intended Audience :: Developers
Classifier: Environment :: Console
Classifier: Typing :: Typed
Classifier: Topic :: Internet :: Proxy Servers
Classifier: Topic :: Utilities
Requires-Python: >=3.8
License-File: LICENSE
Requires-Dist: requests>=2.28
Requires-Dist: pysocks>=1.7
Dynamic: license-file
